CHANGES.rst
LICENSE.txt
MANIFEST.in
README.rst
setup.py
src/normalize_cz_unicode/__init__.py
src/normalize_cz_unicode.egg-info/PKG-INFO
src/normalize_cz_unicode.egg-info/SOURCES.txt
src/normalize_cz_unicode.egg-info/dependency_links.txt
src/normalize_cz_unicode.egg-info/requires.txt
src/normalize_cz_unicode.egg-info/top_level.txt
src/normalize_cz_unicode.egg-info/zip-safe
tests/test_normalize.py