Metadata-Version: 1.1
Name: normalize-cz-unicode
Version: 1.0.0
Summary: Take unicode string, leave czech characters, normalize rest.
Home-page: https://github.com/Bystroushaak/normalize_cz_unicode
Author: Bystroushaak
Author-email: bystrousak@kitakitsune.org
License: MIT
Platform: UNKNOWN
Classifier: Intended Audience :: Developers
Classifier: Programming Language :: Python :: 2
Classifier: Programming Language :: Python :: 2.7
Classifier: License :: OSI Approved :: MIT License
Classifier: Development Status :: 5 - Production/Stable
Classifier: Natural Language :: Czech
Classifier: Topic :: Text Processing
Classifier: Topic :: Text Processing :: General
